aliyunsdkdas/__init__.py
aliyunsdkdas/endpoint.py
aliyunsdkdas/request/__init__.py
aliyunsdkdas/request/v20200116/AddHDMInstanceRequest.py
aliyunsdkdas/request/v20200116/CreateAdamBenchTaskRequest.py
aliyunsdkdas/request/v20200116/CreateCacheAnalysisJobRequest.py
aliyunsdkdas/request/v20200116/CreateCloudBenchTasksRequest.py
aliyunsdkdas/request/v20200116/CreateDiagnosticReportRequest.py
aliyunsdkdas/request/v20200116/CreateKillInstanceSessionTaskRequest.py
aliyunsdkdas/request/v20200116/CreateKillInstanceSessionTaskWithMaintainUserRequest.py
aliyunsdkdas/request/v20200116/CreateQueryOptimizeTagRequest.py
aliyunsdkdas/request/v20200116/CreateRequestDiagnosisRequest.py
aliyunsdkdas/request/v20200116/DeleteCloudBenchTaskRequest.py
aliyunsdkdas/request/v20200116/DeleteStopGatewayRequest.py
aliyunsdkdas/request/v20200116/DescribeAutoScalingConfigRequest.py
aliyunsdkdas/request/v20200116/DescribeAutoScalingHistoryRequest.py
aliyunsdkdas/request/v20200116/DescribeCacheAnalysisJobRequest.py
aliyunsdkdas/request/v20200116/DescribeCacheAnalysisJobsRequest.py
aliyunsdkdas/request/v20200116/DescribeCloudBenchTasksRequest.py
aliyunsdkdas/request/v20200116/DescribeCloudbenchTaskConfigRequest.py
aliyunsdkdas/request/v20200116/DescribeCloudbenchTaskRequest.py
aliyunsdkdas/request/v20200116/DescribeDiagnosticReportListRequest.py
aliyunsdkdas/request/v20200116/DescribeHotBigKeysRequest.py
aliyunsdkdas/request/v20200116/DescribeHotKeysRequest.py
aliyunsdkdas/request/v20200116/DescribeInstanceDasProRequest.py
aliyunsdkdas/request/v20200116/DescribeTopBigKeysRequest.py
aliyunsdkdas/request/v20200116/DescribeTopHotKeysRequest.py
aliyunsdkdas/request/v20200116/DisableAllSqlConcurrencyControlRulesRequest.py
aliyunsdkdas/request/v20200116/DisableAutoResourceOptimizeRulesRequest.py
aliyunsdkdas/request/v20200116/DisableAutoThrottleRulesRequest.py
aliyunsdkdas/request/v20200116/DisableDasProRequest.py
aliyunsdkdas/request/v20200116/DisableInstanceDasConfigRequest.py
aliyun_python_sdk_das-2.0.36.dist-info/LICENSE
aliyun_python_sdk_das-2.0.36.dist-info/METADATA
aliyun_python_sdk_das-2.0.36.dist-info/WHEEL
aliyun_python_sdk_das-2.0.36.dist-info/top_level.txt
aliyun_python_sdk_das-2.0.36.dist-info/RECORD
